tb.py
tb_setup.py
tbcore.py
terrabuddy-0.1.dist-info/METADATA
terrabuddy-0.1.dist-info/WHEEL
terrabuddy-0.1.dist-info/entry_points.txt
terrabuddy-0.1.dist-info/top_level.txt
terrabuddy-0.1.dist-info/RECORD
