Metadata-Version: 2.1
Name: terrabuddy
Version: 0.1
Summary: A python wrapper for multipass
Home-page: https://github.com/jumidev/terrabuddy
Author: krezreb
Author-email: josephbeeson@gmail.com
License: MIT
Platform: UNKNOWN
Requires-Dist: PyCryptodome
Requires-Dist: azure-cli
Requires-Dist: azure-storage-blob
Requires-Dist: boto3
Requires-Dist: fuzzywuzzy
Requires-Dist: gitpython
Requires-Dist: prompt-toolkit
Requires-Dist: pyfiglet
Requires-Dist: pyhcl
Requires-Dist: python-Levenshtein
Requires-Dist: python-dotenv
Requires-Dist: pyyaml
Requires-Dist: requests
Requires-Dist: urllib3 (<2)
